pyscanf/__init__.py
pyscanf/tests/test___init__.py
pyscanf-0.0.1.1.dist-info/LICENSE
pyscanf-0.0.1.1.dist-info/METADATA
pyscanf-0.0.1.1.dist-info/WHEEL
pyscanf-0.0.1.1.dist-info/top_level.txt
pyscanf-0.0.1.1.dist-info/RECORD
